isHex.py
isHex-1.1.0.dist-info/LICENSE
isHex-1.1.0.dist-info/METADATA
isHex-1.1.0.dist-info/WHEEL
isHex-1.1.0.dist-info/top_level.txt
isHex-1.1.0.dist-info/RECORD
